[
    1,
    0,
    0,
    [
        [
            "cc.Mesh",
            [
                "_native",
                "_dataLength",
                "_hash",
                "_struct"
            ],
            0,
            11
        ]
    ],
    [
        [
            0,
            0,
            1,
            2,
            3,
            4
        ]
    ],
    [
        [
            0,
            ".bin",
            69264,
            3545705047,
            [
                {
                    "primitives": [
                        {
                            "primitiveMode": 7,
                            "vertexBundelIndices": [
                                0
                            ],
                            "indexView": {
                                "offset": 50544,
                                "length": 18720,
                                "count": 4680,
                                "stride": 4
                            }
                        }
                    ],
                    "vertexBundles": [
                        {
                            "view": {
                                "offset": 0,
                                "length": 50544,
                                "count": 1053,
                                "stride": 48
                            },
                            "attributes": [
                                {
                                    "name": "a_position",
                                    "format": 32,
                                    "isNormalized": false
                                },
                                {
                                    "name": "a_normal",
                                    "format": 32,
                                    "isNormalized": false
                                },
                                {
                                    "name": "a_texCoord",
                                    "format": 21,
                                    "isNormalized": false
                                },
                                {
                                    "name": "a_tangent",
                                    "format": 44,
                                    "isNormalized": false
                                }
                            ]
                        }
                    ]
                },
                "minPosition",
                8,
                [
                    1,
                    -0.3609479069709778,
                    -0.004696310963481665,
                    -0.06647580862045288
                ],
                "maxPosition",
                8,
                [
                    1,
                    -0.31964027881622314,
                    0.3926851749420166,
                    -0.017409613355994225
                ]
            ]
        ]
    ],
    0,
    0,
    [],
    [],
    []
]
