{
  "__type__": "cc.Mesh",
  "_name": "",
  "_objFlags": 0,
  "_native": ".bin",
  "_struct": {
    "primitives": [
      {
        "primitiveMode": 7,
        "vertexBundelIndices": [
          0
        ],
        "indexView": {
          "offset": 2064,
          "length": 768,
          "count": 192,
          "stride": 4
        }
      }
    ],
    "vertexBundles": [
      {
        "view": {
          "offset": 0,
          "length": 2064,
          "count": 43,
          "stride": 48
        },
        "attributes": [
          {
            "name": "a_position",
            "format": 32,
            "isNormalized": false
          },
          {
            "name": "a_normal",
            "format": 32,
            "isNormalized": false
          },
          {
            "name": "a_texCoord",
            "format": 21,
            "isNormalized": false
          },
          {
            "name": "a_tangent",
            "format": 44,
            "isNormalized": false
          }
        ]
      }
    ],
    "minPosition": {
      "__type__": "cc.Vec3",
      "x": -0.4737553894519806,
      "y": 0.003978000022470951,
      "z": 0.5206922292709351
    },
    "maxPosition": {
      "__type__": "cc.Vec3",
      "x": -0.3400229215621948,
      "y": 0.20346450805664062,
      "z": 0.6883506774902344
    }
  },
  "_dataLength": 2832,
  "_hash": 1686659314
}