{
  "__type__": "cc.Mesh",
  "_name": "",
  "_objFlags": 0,
  "_native": ".bin",
  "_struct": {
    "primitives": [
      {
        "primitiveMode": 7,
        "vertexBundelIndices": [
          0
        ],
        "indexView": {
          "offset": 23184,
          "length": 6120,
          "count": 1530,
          "stride": 4
        }
      }
    ],
    "vertexBundles": [
      {
        "view": {
          "offset": 0,
          "length": 23184,
          "count": 483,
          "stride": 48
        },
        "attributes": [
          {
            "name": "a_position",
            "format": 32,
            "isNormalized": false
          },
          {
            "name": "a_normal",
            "format": 32,
            "isNormalized": false
          },
          {
            "name": "a_texCoord",
            "format": 21,
            "isNormalized": false
          },
          {
            "name": "a_tangent",
            "format": 44,
            "isNormalized": false
          }
        ]
      }
    ],
    "minPosition": {
      "__type__": "cc.Vec3",
      "x": 0.35557225346565247,
      "y": -0.024271802976727486,
      "z": 0.03160242363810539
    },
    "maxPosition": {
      "__type__": "cc.Vec3",
      "x": 0.5093101859092712,
      "y": 0.02893485501408577,
      "z": 0.16408076882362366
    }
  },
  "_dataLength": 29304,
  "_hash": 1385276219
}